odoo_env_config/__init__.py
odoo_env_config/_version.py
odoo_env_config/api.py
odoo_env_config/cli.py
odoo_env_config/entry.py
odoo_env_config/exceptions.py
odoo_env_config/mappers.py
odoo_env_config/utils.py
odoo_env_config/odoo_modules/env2config/__init__.py
odoo_env_config/odoo_modules/env2config/__manifest__.py
odoo_env_config/odoo_modules/env2config/cli/__init__.py
odoo_env_config/section/__init__.py
odoo_env_config/section/addons_path_section.py
odoo_env_config/section/db_section.py
odoo_env_config/section/http_section.py
odoo_env_config/section/limit_section.py
odoo_env_config/section/log_section.py
odoo_env_config/section/misc_section.py
odoo_env_config/section/odoo_opt_section.py
odoo_env_config/section/s3_section.py
odoo_env_config/section/test_section.py
odoo_env_config/section/update_init_section.py
odoo_env_config/section/widemodule_section.py
odoo_env_config/section/worker_section.py
oenv2config-1.8.0.dist-info/METADATA
oenv2config-1.8.0.dist-info/WHEEL
oenv2config-1.8.0.dist-info/entry_points.txt
oenv2config-1.8.0.dist-info/top_level.txt
oenv2config-1.8.0.dist-info/RECORD
