Metadata-Version: 2.4
Name: oenv2config
Version: 1.8.0
Classifier: Programming Language :: Python :: 3
Classifier: Programming Language :: Python :: 3.7
Classifier: Programming Language :: Python :: 3.8
Classifier: Programming Language :: Python :: 3.9
Classifier: Programming Language :: Python :: 3.10
Classifier: Programming Language :: Python :: 3.11
Classifier: Programming Language :: Python :: 3.12
Classifier: Programming Language :: Python :: 3 :: Only
Requires-Python: >=3.7
Requires-Dist: addons-installer~=3.8
Requires-Dist: python-dotenv~=1.0; python_version > "3.7"
Requires-Dist: python-dotenv==0.21.1; python_version == "3.7"
Requires-Dist: typing-extensions<5,>=4.3.0
